{
  "project_info": {
    "project_number": "269282291320",
    "project_id": "gamehostingservice",
    "storage_bucket": "gamehostingservice.firebasestorage.app"
  },
  "client": [
    {
      "client_info": {
        "mobilesdk_app_id": "1:269282291320:android:3ad3b64b6988063e69078d",
        "android_client_info": {
          "package_name": "com.myreactnativeapp"
        }
      },
      "oauth_client": [],
      "api_key": [
        {
          "current_key": "AIzaSyDVXUwg0hb9VW29E7FAbs4DdtT8JR5A3Vw"
        }
      ],
      "services": {
        "appinvite_service": {
          "other_platform_oauth_client": []
        }
      }
    }
  ],
  "configuration_version": "1"
}